TKImageButton/TKImageButton.py
TKImageButton/__init__.py
TKImageButton-0.0.1.dist-info/LICENSE
TKImageButton-0.0.1.dist-info/METADATA
TKImageButton-0.0.1.dist-info/WHEEL
TKImageButton-0.0.1.dist-info/top_level.txt
TKImageButton-0.0.1.dist-info/RECORD
